catalog_api_client/__init__.py
catalog_api_client/api/__init__.py
catalog_api_client/api/product/__init__.py
catalog_api_client/api/product/get_product.py
catalog_api_client/api/product_summary/__init__.py
catalog_api_client/api/product_summary/search.py
catalog_api_client/client.py
catalog_api_client/errors.py
catalog_api_client/models/__init__.py
catalog_api_client/models/aspect.py
catalog_api_client/models/aspect_distribution.py
catalog_api_client/models/aspect_value_distribution.py
catalog_api_client/models/error.py
catalog_api_client/models/error_parameter.py
catalog_api_client/models/image.py
catalog_api_client/models/product.py
catalog_api_client/models/product_search_response.py
catalog_api_client/models/product_summary.py
catalog_api_client/models/refinement.py
catalog_api_client/py.typed
catalog_api_client/types.py
catalog_api_client-0.1.dist-info/licenses/LICENSE
catalog_api_client-0.1.dist-info/METADATA
catalog_api_client-0.1.dist-info/WHEEL
catalog_api_client-0.1.dist-info/RECORD
